{
	"name":"Epic Heroism (21st level)",
	"type":"feature",
	"img":"icons/svg/mystery-man.svg",
	"system":{
		"description":{
			"value":"<p>You increase two different ability scores by 2. </p>",
			"chat":"",
			"unidentified":""
		},
		"source":"",
		"macro":{
			"type":"script",
			"scope":"global",
			"launchOrder":"off",
			"command":"",
			"author":""
		},
		"requirements":"",
		"level":"",
		"recharge":{
			"value":null,
			"charged":false
		},
		"featureType":"destiny"
	},
	"effects":[],
	"folder":null,
	"sort":0,
	"flags":{},
	"_id":"u56JTEabLPq3ARt8",
	"_key":"!items!u56JTEabLPq3ARt8"
}