{
	"_id":"Px6bO02YHCZIVaig",
	"name":"Avenger 06-Freedom Step",
	"type":"power",
	"img":"modules/dnd-4e-compendium/icons/powers/encounter_move_instant.png",
	"effects":[],
	"folder":null,
	"sort":0,
	"flags":{},
	"system":{
		"description":{
			"value":"<p class=\"flavour\"><i>You blur into motion, moving faster than the eye can follow.</i></p><p class=\"power-basics\"><b>Encounter ✦ Divine</b></p><p class=\"power-basics\"><b>Move Action</b><b> &#8226; </b>Personal</p><p><b>Prerequisite:</b> Godsworn Alacrity </p><p><b>Effect:</b> If you are slowed, immobilized, or restrained, the condition ends. You shift a number of squares equal to your speed. </p><p>Published in Dragon Magazine 384, page(s) 44. </p>",
			"chat":"",
			"unidentified":""
		},
		"source":"",
		"activation":{
			"type":"",
			"cost":0,
			"condition":""
		},
		"duration":{
			"value":null,
			"units":""
		},
		"target":"",
		"range":{
			"value":null,
			"long":null,
			"units":""
		},
		"uses":{
			"value":1,
			"max":"1",
			"per":"enc"
		},
		"consume":{
			"type":"",
			"target":"",
			"amount":null
		},
		"macro":{
			"type":"script",
			"scope":"global",
			"launchOrder":"off",
			"command":"",
			"author":""
		},
		"attack":{
			"shareAttackRoll":false,
			"isAttack":false,
			"ability":"",
			"abilityBonus":0,
			"def":"",
			"defBonus":0,
			"formula":"",
			"damageType":{},
			"effectType":{}
		},
		"hit":{
			"shareDamageRoll":false,
			"isDamage":false,
			"isHealing":false,
			"healSurge":"",
			"baseQuantity":"",
			"baseDiceType":"",
			"detail":"",
			"formula":"@powBase + @wepDamage + @dmgMod",
			"critFormula":"@powMax + @wepDamage + @wepCritBonus + @dmgMod",
			"healFormula":""
		},
		"miss":{
			"detail":"",
			"formula":""
		},
		"effect":{
			"detail":"If you are slowed, immobilized, or restrained, the condition ends. You shift a number of squares equal to your speed."
		},
		"damage":{
			"parts":[]
		},
		"damageCrit":{
			"parts":[]
		},
		"damageImp":{
			"parts":[]
		},
		"damageCritImp":{
			"parts":[]
		},
		"keyWords":[
			"Divine"
		],
		"level":"6",
		"powersource":"divine",
		"secondPowersource":"",
		"subName":"Avenger Utility 6",
		"prepared":true,
		"powerType":"class",
		"powerSubtype":"utility",
		"useType":"encounter",
		"actionType":"move",
		"requirements":"",
		"weaponType":"none",
		"weaponUse":"default",
		"rangeType":"personal",
		"rangeTextShort":"",
		"rangeText":"",
		"rangePower":null,
		"area":null,
		"rechargeRoll":"",
		"rechargeCondition":"",
		"damageShare":false,
		"postEffect":true,
		"postSpecial":true,
		"autoGenChatPowerCard":false,
		"sustain":{
			"actionType":"",
			"detail":""
		},
		"trigger":"",
		"requirement":"",
		"special":"Prerequisite: Godsworn Alacrity",
		"specialAdd":{
			"parts":[]
		},
		"damageType":{
			"damage":false,
			"acid":false,
			"cold":false,
			"fire":false,
			"force":false,
			"lightning":false,
			"necrotic":false,
			"physical":false,
			"poison":false,
			"psychic":false,
			"radiant":false,
			"thunder":false
		},
		"effectHTML":false,
		"effectType":{
			"beast":false,
			"beastForm":false,
			"charm":false,
			"conjuration":false,
			"fear":false,
			"healing":false,
			"illusion":false,
			"invigorating":false,
			"poison":false,
			"polymorph":false,
			"rage":false,
			"rattling":false,
			"reliable":false,
			"sleep":false,
			"spirit":false,
			"stance":false,
			"summoning":false,
			"teleportation":false,
			"zone":false,
			"augmentable":false,
			"aura":false,
			"channelDiv":false,
			"disease":false,
			"elemental":false,
			"enchantment":false,
			"evocation":false,
			"fullDis":false,
			"gaze":false,
			"mount":false,
			"necro":false,
			"nether":false,
			"runic":false,
			"transmutation":false
		},
		"chatFlavor":"You blur into motion, moving faster than the eye can follow."
	},
	"_key":"!items!Px6bO02YHCZIVaig"
}