{
	"name":"Defensive Resilience",
	"type":"feature",
	"img":"icons/svg/mystery-man.svg",
	"system":{
		"description":{
			"value":"<p><b>Prerequisite: </b>Con 13, Wis 13, fighter </p><p><b>Benefit: </b>When you use second wind while you are bloodied, you gain a +1 bonus to all defenses, in addition to the normal bonus for second wind, until the end of your next turn. </p><p>Published in Martial Power, page(s) 133. </p>",
			"chat":"",
			"unidentified":""
		},
		"source":"",
		"macro":{
			"type":"script",
			"scope":"global",
			"launchOrder":"off",
			"command":"",
			"author":""
		},
		"requirements":"",
		"level":"",
		"recharge":{
			"value":null,
			"charged":false
		},
		"featureType":"feat"
	},
	"effects":[],
	"folder":null,
	"sort":0,
	"flags":{},
	"_id":"StqfMg7vHaWoRkiV",
	"_key":"!items!StqfMg7vHaWoRkiV"
}