{
	"name":"Secret Stride",
	"type":"feature",
	"img":"icons/svg/mystery-man.svg",
	"system":{
		"description":{
			"value":"<p><b>Prerequisite: </b>11th level, Trained in Stealth </p><p><b>Benefit: </b>You don't take the -5 penalty to Stealth checks for moving more than 2 squares. </p><p>Revision (7/28/2008) </p><p>Replace Benefits text with \"You don't take the -5 penalty to Stealth checks for moving more than 2 squares.\" </p><p>Published in Player's Handbook, page(s) 205. </p>",
			"chat":"",
			"unidentified":""
		},
		"source":"",
		"macro":{
			"type":"script",
			"scope":"global",
			"launchOrder":"off",
			"command":"",
			"author":""
		},
		"requirements":"",
		"level":"",
		"recharge":{
			"value":null,
			"charged":false
		},
		"featureType":"feat"
	},
	"effects":[],
	"folder":null,
	"sort":0,
	"flags":{},
	"_id":"04FOdPpckbsgEWHy",
	"_key":"!items!04FOdPpckbsgEWHy"
}