{
	"name":"Robe of Defying Storms +3",
	"type":"equipment",
	"img":"modules/dnd-4e-compendium/icons/armor/cloth3.webp",
	"system":{
		"description":{
			"value":"<p class=\"flavour\"><i>Embroidered patterns on these robes resemble clouds and great, slashing bursts of lightning. You gain both protection from storms and the ability to call upon their power.</i></p><p class=\"basics\"><b>Armor</b><b>:</b> Cloth</p>\n<p class=\"basics\"><b>Enhancement Bonus:</b> AC</p>\n<p class=\"subheading\"><b>Property:</b></p> <p>Resist 10 lightning and resist 10 thunder.</p><p>Level 24 or 29: Resist 15 and Resist 15</p>\n<p class=\"subheading\"><b>Power ✦ Daily (Immediate Interrupt)</b></p><p>Use this power when you would take lightning or thunder damage. You take no lightning or thunder damage, you gain a +1 power bonus to attack rolls until the end of your next turn, and you can spend a healing surge.</p>",
			"chat":"",
			"unidentified":""
		},
		"source":"",
		"quantity":1,
		"weight":4,
		"price":21000,
		"attuned":false,
		"equipped":true,
		"rarity":"",
		"identified":true,
		"activation":{
			"type":"",
			"cost":0,
			"condition":""
		},
		"duration":{
			"value":null,
			"units":""
		},
		"target":{
			"value":null,
			"width":null,
			"units":"",
			"type":""
		},
		"range":{
			"value":null,
			"long":null,
			"units":""
		},
		"uses":{
			"value":0,
			"max":0,
			"per":null
		},
		"consume":{
			"type":"",
			"target":null,
			"amount":null
		},
		"armour":{
			"value":10,
			"type":"armour",
			"subType":"light",
			"ac":0,
			"fort":0,
			"ref":0,
			"wil":0,
			"dex":null,
			"movePen":false,
			"movePenValue":0,
			"skillCheck":false,
			"skillCheckValue":0,
			"enhance":3
		},
		"hp":{
			"value":0,
			"max":0,
			"dt":null,
			"conditions":""
		},
		"macro":{
			"type":"script",
			"scope":"global",
			"launchOrder":"off",
			"command":"",
			"author":""
		},
		"level":"14",
		"speed":{
			"value":null,
			"conditions":""
		},
		"strength":0,
		"stealth":false,
		"proficient":true
	},
	"effects":[],
	"folder":null,
	"sort":0,
	"flags":{},
	"_id":"65ofr1Rgi2yVBIwT",
	"_key":"!items!65ofr1Rgi2yVBIwT"
}