{
	"name":"empowered crit",
	"_id":"JPEqOa6NyCAgxhQU",
	"pages":[
		{
			"sort":100000,
			"name":"empowered crit",
			"type":"text",
			"_id":"aKeg41FCbMIA79Xs",
			"title":{
				"show":false,
				"level":1
			},
			"image":{},
			"text":{
				"format":1,
				"content":"<h1>empowered crit</h1><p>When you score a critical hit with an implement attack using an empowered crit implement, the attack deals 1d10 extra damage (this damage is not maximized). The extra damage increases to 2d10 at 11th level and 3d10 at 21st level.</p><p>Published in Mordenkainen's Magnificent Emporium, page(s) 41.</p>"
			},
			"src":null,
			"system":{},
			"flags":{},
			"_key":"!journal.pages!JPEqOa6NyCAgxhQU.aKeg41FCbMIA79Xs"
		}
	],
	"folder":null,
	"sort":0,
	"flags":{},
	"_key":"!journal!JPEqOa6NyCAgxhQU"
}