{
	"name":"god",
	"_id":"Hfs9VXe3t5OTmyZn",
	"pages":[
		{
			"sort":100000,
			"name":"god",
			"type":"text",
			"_id":"Kz4VFWjYmDUJ2tNP",
			"title":{
				"show":false,
				"level":1
			},
			"image":{},
			"text":{
				"format":1,
				"content":"<h1>god</h1><p></p><p class=\"publishedIn\">Published in Monster Manual 3.</p>"
			},
			"src":null,
			"system":{},
			"flags":{},
			"_key":"!journal.pages!Hfs9VXe3t5OTmyZn.Kz4VFWjYmDUJ2tNP"
		}
	],
	"folder":null,
	"sort":0,
	"flags":{},
	"_key":"!journal!Hfs9VXe3t5OTmyZn"
}